{"place_id": 280442771, "licence": "Data \u00a9 OpenStreetMap contributors, ODbL 1.0. http://osm.org/copyright", "osm_type": "way", "osm_id": 451984384, "lat": "51.5025387", "lon": "-0.1477618", "category": "highway", "type": "cycleway", "place_rank": 27, "importance": 0.040093079270618746, "addresstype": "road", "name": "Constitution Hill", "display_name": "Constitution Hill, Belgravia, City of Westminster, Greater London, England, WC2E 9DA, United Kingdom", "address": {"road": "Constitution Hill", "suburb": "Belgravia", "city": "City of Westminster", "ISO3166-2-lvl8": "GB-WSM", "state": "England", "ISO3166-2-lvl4": "GB-ENG", "postcode": "WC2E 9DA", "country": "United Kingdom", "country_code": "gb"}, "boundingbox": ["51.5023269", "51.5025940", "-0.1492341", "-0.1422007"]}