{"place_id": 281487274, "licence": "Data \u00a9 OpenStreetMap contributors, ODbL 1.0. http://osm.org/copyright", "osm_type": "node", "osm_id": 6209023201, "lat": "51.5026319", "lon": "-0.1353530", "category": "information", "type": "guidepost", "place_rank": 30, "importance": 9.307927061870783e-05, "addresstype": "information", "name": "", "display_name": "Blue Bridge, Westminster, Victoria, City of Westminster, Greater London, England, SW1A 1BJ, United Kingdom", "address": {"road": "Blue Bridge", "quarter": "Westminster", "suburb": "Victoria", "city": "City of Westminster", "ISO3166-2-lvl8": "GB-WSM", "state": "England", "ISO3166-2-lvl4": "GB-ENG", "postcode": "SW1A 1BJ", "country": "United Kingdom", "country_code": "gb"}, "boundingbox": ["51.5025819", "51.5026819", "-0.1354030", "-0.1353030"]}