{"place_id": 280364296, "licence": "Data \u00a9 OpenStreetMap contributors, ODbL 1.0. http://osm.org/copyright", "osm_type": "way", "osm_id": 740961040, "lat": "51.4835989", "lon": "-0.1322389", "category": "highway", "type": "pedestrian", "place_rank": 26, "importance": 0.053426412603952055, "addresstype": "road", "name": "Bourne Valley Wharf", "display_name": "Bourne Valley Wharf, Nine Elms, London Borough of Wandsworth, Greater London, England, SW8 5DB, United Kingdom", "address": {"road": "Bourne Valley Wharf", "quarter": "Nine Elms", "city_district": "London Borough of Wandsworth", "ISO3166-2-lvl8": "GB-WND", "city": "Greater London", "state": "England", "ISO3166-2-lvl4": "GB-ENG", "postcode": "SW8 5DB", "country": "United Kingdom", "country_code": "gb"}, "boundingbox": ["51.4834520", "51.4837529", "-0.1325116", "-0.1319144"]}