{"place_id": 278862003, "licence": "Data \u00a9 OpenStreetMap contributors, ODbL 1.0. http://osm.org/copyright", "osm_type": "way", "osm_id": 97209876, "lat": "51.4909644", "lon": "-0.1153757", "category": "building", "type": "yes", "place_rank": 30, "importance": 9.307927061870783e-05, "addresstype": "building", "name": "Beckham House", "display_name": "Beckham House, Beaufoy Walk, Ethelred Estate, Lambeth, London Borough of Lambeth, Greater London, England, SE11 6UB, United Kingdom", "address": {"building": "Beckham House", "road": "Beaufoy Walk", "neighbourhood": "Ethelred Estate", "suburb": "Lambeth", "city_district": "London Borough of Lambeth", "ISO3166-2-lvl8": "GB-LBH", "city": "Greater London", "state": "England", "ISO3166-2-lvl4": "GB-ENG", "postcode": "SE11 6UB", "country": "United Kingdom", "country_code": "gb"}, "boundingbox": ["51.4908572", "51.4910866", "-0.1156077", "-0.1151446"]}