{"place_id": 283123152, "licence": "Data \u00a9 OpenStreetMap contributors, ODbL 1.0. http://osm.org/copyright", "osm_type": "relation", "osm_id": 18350645, "lat": "51.4927832", "lon": "-0.1356715", "category": "leisure", "type": "track", "place_rank": 30, "importance": 9.307927061870783e-05, "addresstype": "leisure", "name": "", "display_name": "Vincent Square, Tachbrook Estate, Westminster, Pimlico, City of Westminster, Greater London, England, SW1V 2RH, United Kingdom", "address": {"road": "Vincent Square", "neighbourhood": "Tachbrook Estate", "quarter": "Westminster", "suburb": "Pimlico", "city": "City of Westminster", "ISO3166-2-lvl8": "GB-WSM", "state": "England", "ISO3166-2-lvl4": "GB-ENG", "postcode": "SW1V 2RH", "country": "United Kingdom", "country_code": "gb"}, "boundingbox": ["51.4924263", "51.4931339", "-0.1357446", "-0.1345636"]}