{"place_id": 280552323, "licence": "Data \u00a9 OpenStreetMap contributors, ODbL 1.0. http://osm.org/copyright", "osm_type": "way", "osm_id": 163034470, "lat": "51.5202551", "lon": "-0.1035035", "category": "amenity", "type": "cafe", "place_rank": 30, "importance": 9.307927061870783e-05, "addresstype": "amenity", "name": "Starbucks", "display_name": "Starbucks, 19-25, Cowcross Street, Farringdon, Islington, London Borough of Islington, Greater London, England, EC1M 6DQ, United Kingdom", "address": {"amenity": "Starbucks", "house_number": "19-25", "road": "Cowcross Street", "neighbourhood": "Farringdon", "suburb": "Islington", "city_district": "London Borough of Islington", "ISO3166-2-lvl8": "GB-ISL", "city": "Greater London", "state": "England", "ISO3166-2-lvl4": "GB-ENG", "postcode": "EC1M 6DQ", "country": "United Kingdom", "country_code": "gb"}, "boundingbox": ["51.5201988", "51.5203369", "-0.1035915", "-0.1034074"]}