{"place_id": 281393585, "licence": "Data \u00a9 OpenStreetMap contributors, ODbL 1.0. http://osm.org/copyright", "osm_type": "node", "osm_id": 10268621525, "lat": "51.5196209", "lon": "-0.1205130", "category": "office", "type": "union", "place_rank": 30, "importance": 9.307927061870783e-05, "addresstype": "office", "name": "Unite The Union Head Office", "display_name": "Unite The Union Head Office, 128, Theobalds Road, Gray's Inn, Holborn, London Borough of Camden, Greater London, England, WC1X 8TN, United Kingdom", "address": {"office": "Unite The Union Head Office", "house_number": "128", "road": "Theobalds Road", "neighbourhood": "Gray's Inn", "suburb": "Holborn", "city_district": "London Borough of Camden", "ISO3166-2-lvl8": "GB-CMD", "city": "Greater London", "state": "England", "ISO3166-2-lvl4": "GB-ENG", "postcode": "WC1X 8TN", "country": "United Kingdom", "country_code": "gb"}, "boundingbox": ["51.5195709", "51.5196709", "-0.1205630", "-0.1204630"]}