{"place_id": 282894884, "licence": "Data \u00a9 OpenStreetMap contributors, ODbL 1.0. http://osm.org/copyright", "osm_type": "way", "osm_id": 96111865, "lat": "51.4953285", "lon": "-0.1133116", "category": "building", "type": "apartments", "place_rank": 30, "importance": 9.307927061870783e-05, "addresstype": "building", "name": "Bristol House", "display_name": "Bristol House, Lambeth Walk, Lambeth, London Borough of Lambeth, Greater London, England, SE11 6LY, United Kingdom", "address": {"building": "Bristol House", "road": "Lambeth Walk", "suburb": "Lambeth", "city_district": "London Borough of Lambeth", "ISO3166-2-lvl8": "GB-LBH", "city": "Greater London", "state": "England", "ISO3166-2-lvl4": "GB-ENG", "postcode": "SE11 6LY", "country": "United Kingdom", "country_code": "gb"}, "boundingbox": ["51.4952309", "51.4954278", "-0.1135747", "-0.1130484"]}