{"place_id": 281691694, "licence": "Data \u00a9 OpenStreetMap contributors, ODbL 1.0. http://osm.org/copyright", "osm_type": "way", "osm_id": 540215910, "lat": "51.4910162", "lon": "-0.1213817", "category": "building", "type": "apartments", "place_rank": 30, "importance": 9.307927061870783e-05, "addresstype": "building", "name": "The Corniche - Tower Three", "display_name": "The Corniche - Tower Three, 20, Albert Embankment, Vauxhall, London Borough of Lambeth, Greater London, England, SE1 7GR, United Kingdom", "address": {"building": "The Corniche - Tower Three", "house_number": "20", "road": "Albert Embankment", "suburb": "Vauxhall", "city_district": "London Borough of Lambeth", "ISO3166-2-lvl8": "GB-LBH", "city": "Greater London", "state": "England", "ISO3166-2-lvl4": "GB-ENG", "postcode": "SE1 7GR", "country": "United Kingdom", "country_code": "gb"}, "boundingbox": ["51.4908936", "51.4912049", "-0.1215696", "-0.1211710"]}