{"version": 0.6, "generator": "Overpass API 0.7.62.11 87bfad18", "osm3s": {"timestamp_osm_base": "2026-06-10T16:33:30Z", "copyright": "The data included in this document is from www.openstreetmap.org. The data is made available under ODbL."}, "elements": [{"type": "node", "id": 264790279, "lat": 51.4957145, "lon": -0.1038594, "tags": {"addr:city": "London", "addr:housenumber": "51", "addr:street": "St George's Road", "amenity": "pub", "check_date": "2026-03-03", "check_date:opening_hours": "2023-02-12", "contact:facebook": "prince.of.wales.se1", "contact:instagram": "prince.of.wales.se1", "name": "Prince of Wales", "opening_hours:signed": "no"}}, {"type": "node", "id": 265241529, "lat": 51.4957918, "lon": -0.1038984, "tags": {"amenity": "post_box", "brand": "Royal Mail", "brand:wikidata": "Q638098", "brand:wikipedia": "en:Royal Mail", "collection_times": "Mo-Fr 18:30, Sa 13:00", "drive_through": "no", "operator": "Royal Mail", "operator:wikidata": "Q638098", "post_box:apertures": "2", "post_box:design": "type_c", "post_box:type": "pillar", "ref": "SE1 80;SE1 180", "royal_cypher": "EIIR", "royal_cypher:wikidata": "Q33102113", "source": "survey"}}, {"type": "node", "id": 265241561, "lat": 51.4959775, "lon": -0.101057, "tags": {"amenity": "telephone", "atm": "yes", "booth": "KXCash", "check_date": "2026-03-06", "colour": "grey"}}, {"type": "node", "id": 544504153, "lat": 51.4974337, "lon": -0.1035282, "tags": {"amenity": "cafe", "check_date": "2026-06-01", "name": "Art Cafe", "name:fa": "\u0627\u0631\u062a \u06a9\u0627\u0641\u06cc"}}, {"type": "node", "id": 566662469, "lat": 51.4972602, "lon": -0.103319, "tags": {"addr:city": "London", "addr:housenumber": "21", "addr:postcode": "SE1 6JX", "addr:street": "London Road", "check_date": "2026-06-01", "name": "The Southbank Art Company", "shop": "gift", "website": "https://southbankart.co.uk/"}}, {"type": "node", "id": 603087609, "lat": 51.495674, "lon": -0.101186, "tags": {"amenity": "bicycle_parking", "description": "Cap 10"}}, {"type": "node", "id": 603088917, "lat": 51.4974154, "lon": -0.1033421, "tags": {"amenity": "bicycle_parking", "bicycle_parking": "stands", "covered": "no"}}, {"type": "node", "id": 802185050, "lat": 51.4956686, "lon": -0.1023189, "tags": {"amenity": "doctors", "healthcare": "doctor", "name": "Princess Street Group Practice"}}, {"type": "node", "id": 869924030, "lat": 51.495727, "lon": -0.0999471, "tags": {"amenity": "bicycle_parking", "bicycle_parking": "stands", "capacity": "10", "covered": "no"}}, {"type": "node", "id": 872350881, "lat": 51.4964857, "lon": -0.1014871, "tags": {"amenity": "bicycle_rental", "bicycle_rental": "docking_station", "brand": "Santander Cycles", "brand:wikidata": "Q807961", "capacity": "16", "check_date": "2025-01-27", "historic:ref": "CH16094", "local": "Elephant & Castle", "name": "Ontario Street", "network": "tfl_cycle_hire", "official_name": "Ontario Street, Elephant & Castle", "official_ref": "324", "operator": "Serco", "operator:type": "private", "operator:wikidata": "Q499104"}}, {"type": "node", "id": 976548467, "lat": 51.496077, "lon": -0.1006691, "tags": {"amenity": "recycling", "recycling:cans": "yes", "recycling:cardboard": "yes", "recycling:paper": "yes"}}, {"type": "node", "id": 1032792739, "lat": 51.494673, "lon": -0.1012302, "tags": {"amenity": "bicycle_parking", "bicycle_parking": "stands", "capacity": "30", "covered": "no"}}, {"type": "node", "id": 2467649380, "lat": 51.4960545, "lon": -0.104211, "tags": {"amenity": "bicycle_rental", "bicycle_rental": "docking_station", "brand": "Santander Cycles", "brand:wikidata": "Q807961", "capacity": "44", "local": "Elephant & Castle", "name": "Gaywood Street", "network": "tfl_cycle_hire", "official_name": "Gaywood Street, Elephant & Castle", "official_ref": "549", "operator": "Serco", "operator:wikidata": "Q499104"}}, {"type": "node", "id": 3300122313, "lat": 51.4960397, "lon": -0.1011141, "tags": {"amenity": "bicycle_parking", "bicycle_parking": "stands", "capacity": "16", "covered": "no"}}, {"type": "node", "id": 3300122314, "lat": 51.4964228, "lon": -0.1011592, "tags": {"access": "private", "amenity": "bicycle_parking", "bicycle_parking": "stands", "capacity": "100", "covered": "yes"}}, {"type": "node", "id": 3306736786, "lat": 51.4950031, "lon": -0.1022482, "tags": {"amenity": "arts_centre", "name": "Nursery Gallery"}}, {"type": "node", "id": 3306736787, "lat": 51.496306, "lon": -0.1047164, "tags": {"amenity": "dentist", "check_date": "2026-03-03", "healthcare": "dentist"}}, {"type": "node", "id": 3447788452, "lat": 51.4953669, "lon": -0.1025767, "tags": {"amenity": "fast_food", "building": "kiosk", "name": "Falafel Lover"}}, {"type": "node", "id": 3447789927, "lat": 51.4953564, "lon": -0.1025201, "tags": {"amenity": "fast_food", "building": "kiosk", "name": "Nandine Coffee"}}, {"type": "node", "id": 4169653678, "lat": 51.49546, "lon": -0.1024776, "tags": {"amenity": "bicycle_parking", "bicycle_parking": "stands", "capacity": "6", "covered": "no"}}, {"type": "node", "id": 4169653679, "lat": 51.4959017, "lon": -0.1039337, "tags": {"amenity": "bicycle_parking", "bicycle_parking": "stands", "capacity": "6", "covered": "no"}}, {"type": "node", "id": 4564372700, "lat": 51.4954192, "lon": -0.1002771, "tags": {"amenity": "bicycle_parking", "bicycle_parking": "stands", "capacity": "16", "covered": "no", "fee": "no"}}, {"type": "node", "id": 5089339229, "lat": 51.4959644, "lon": -0.101087, "tags": {"amenity": "atm", "brand": "Cashzone", "brand:wikidata": "Q110738461", "cash_in": "no", "check_date": "2026-06-08", "network": "Allpoint", "network:wikidata": "Q4733264", "operator": "Cash Zone"}}, {"type": "node", "id": 5335951319, "lat": 51.4952385, "lon": -0.1022213, "tags": {"amenity": "bicycle_parking", "bicycle_parking": "stands", "capacity": "56", "covered": "no"}}, {"type": "node", "id": 5335951467, "lat": 51.4952129, "lon": -0.102316, "tags": {"amenity": "bicycle_parking", "bicycle_parking": "stands", "capacity": "20", "covered": "yes"}}, {"type": "node", "id": 6019344419, "lat": 51.496457, "lon": -0.1000811, "tags": {"amenity": "waste_basket", "check_date": "2025-12-16"}}, {"type": "node", "id": 6495023793, "lat": 51.4959091, "lon": -0.100431, "tags": {"amenity": "bench", "armrest": "yes", "backrest": "yes"}}, {"type": "node", "id": 6804159104, "lat": 51.4949006, "lon": -0.1015895, "tags": {"amenity": "bicycle_parking", "bicycle_parking": "stands", "covered": "no"}}, {"type": "node", "id": 7012714393, "lat": 51.494989, "lon": -0.1005403, "tags": {"amenity": "bicycle_parking"}}, {"type": "node", "id": 8879625573, "lat": 51.4954321, "lon": -0.1014758, "tags": {"addr:city": "London", "addr:housename": "Perronet House", "addr:street": "Elephant and Castle", "amenity": "cafe", "internet_access": "wlan", "name": "Black Cowboy Coffee", "phone": "+44 7947 114683", "website": "www.blackcowboy.coffee"}}, {"type": "node", "id": 8942303842, "lat": 51.4948042, "lon": -0.1015116, "tags": {"amenity": "bench"}}, {"type": "node", "id": 8942303843, "lat": 51.4948282, "lon": -0.1014666, "tags": {"amenity": "bench"}}, {"type": "node", "id": 8942303844, "lat": 51.4948342, "lon": -0.1014131, "tags": {"amenity": "bench", "backrest": "yes"}}, {"type": "node", "id": 8942303845, "lat": 51.4948582, "lon": -0.101365, "tags": {"amenity": "bench", "backrest": "yes"}}, {"type": "node", "id": 8942303846, "lat": 51.4947383, "lon": -0.1015073, "tags": {"amenity": "bench"}}, {"type": "node", "id": 8942303847, "lat": 51.4947476, "lon": -0.101472, "tags": {"amenity": "bench"}}, {"type": "node", "id": 8942303848, "lat": 51.4947556, "lon": -0.1015843, "tags": {"amenity": "bench"}}, {"type": "node", "id": 9401357641, "lat": 51.4950365, "lon": -0.1025051, "tags": {"access": "private", "amenity": "bicycle_parking", "bicycle_parking": "shed", "capacity": "6", "check_date": "2026-06-09", "covered": "yes", "operator": "cyclehoop", "ref": "Bikehangar 622"}}, {"type": "node", "id": 10275602154, "lat": 51.4944444, "lon": -0.102515, "tags": {"amenity": "bicycle_parking", "bicycle_parking": "stands", "capacity": "18", "ref:GB:tflcid": "RWG081305"}}, {"type": "node", "id": 10275602297, "lat": 51.4946694, "lon": -0.1024212, "tags": {"amenity": "bicycle_parking", "bicycle_parking": "stands", "capacity": "10", "ref:GB:tflcid": "RWG081205"}}, {"type": "node", "id": 10275607594, "lat": 51.4945879, "lon": -0.1024386, "tags": {"amenity": "bicycle_parking", "bicycle_parking": "stands", "capacity": "10", "ref:GB:tflcid": "RWG081206"}}, {"type": "node", "id": 10275607595, "lat": 51.4958222, "lon": -0.1019753, "tags": {"amenity": "bicycle_parking", "bicycle_lock": "bring_own", "bicycle_parking": "lockers", "capacity": "6", "ref:GB:tflcid": "RWG080907"}}, {"type": "node", "id": 10275607599, "lat": 51.4958151, "lon": -0.1004831, "tags": {"amenity": "bicycle_parking", "bicycle_parking": "post_hoop", "capacity": "2", "ref:GB:tflcid": "RWG150729"}}, {"type": "node", "id": 10277991951, "lat": 51.4975251, "lon": -0.1038086, "tags": {"amenity": "bicycle_parking", "bicycle_parking": "stands", "capacity": "2", "ref:GB:tflcid": "RWG080816"}}, {"type": "node", "id": 10277992228, "lat": 51.4957682, "lon": -0.1038187, "tags": {"amenity": "bicycle_parking", "bicycle_parking": "stands", "capacity": "2", "covered": "no", "ref:GB:tflcid": "RWG080984"}}, {"type": "node", "id": 10277995441, "lat": 51.4962596, "lon": -0.1045755, "tags": {"amenity": "bicycle_parking", "bicycle_parking": "stands", "capacity": "6", "ref:GB:tflcid": "RWG080820"}}, {"type": "node", "id": 10277995621, "lat": 51.4970711, "lon": -0.1024645, "tags": {"amenity": "bicycle_parking", "bicycle_parking": "stands", "capacity": "12", "covered": "no", "ref:GB:tflcid": "RWG081294"}}, {"type": "node", "id": 10975152878, "lat": 51.4975835, "lon": -0.1021858, "tags": {"amenity": "university", "description": "Located on levels 3-4", "name": "University Library", "operator": "London South Bank University", "wheelchair": "limited", "wheelchair:description": "Main door intercom not accessible. the building need automatic door. spacious accessible toilet. lift to gallery accessible but button for the lift need adjudtnebt"}}, {"type": "node", "id": 10975152879, "lat": 51.4976817, "lon": -0.1031255, "tags": {"amenity": "university", "check_date": "2025-08-17", "education": "university", "level": "1;2", "name": "LSBU Active", "operator": "London South Bank University", "wheelchair": "limited", "wheelchair:description": "Main door intercom not accessible. the building need automatic door. spacious accessible toilet. lift to gallery accessible but button for the lift need adjustment"}}, {"type": "node", "id": 11162895313, "lat": 51.4954261, "lon": -0.1015349, "tags": {"amenity": "pharmacy", "healthcare": "pharmacy", "name": "St George", "wheelchair": "yes"}}, {"type": "node", "id": 12536529513, "lat": 51.4958367, "lon": -0.1008864, "tags": {"addr:housenumber": "70-74", "addr:interpolation": "even", "addr:street": "London Road", "check_date": "2026-06-08", "level": "0", "name": "Jazz News", "shop": "newsagent", "wheelchair": "no"}}, {"type": "node", "id": 12803170365, "lat": 51.4952526, "lon": -0.1002529, "tags": {"amenity": "bicycle_parking", "bicycle_parking": "stands", "capacity": "44", "covered": "no", "fee": "no"}}, {"type": "node", "id": 12997774504, "lat": 51.4974018, "lon": -0.1039252, "tags": {"addr:city": "London", "addr:housename": "The Albert Arms", "addr:housenumber": "1", "addr:postcode": "SE1 6EY", "addr:street": "Gladstone Street", "amenity": "pub", "check_date": "2025-05-07", "contact:facebook": "thealbertarms.se1", "contact:instagram": "thealbertarms.se1", "email": "thealbertarms.se1@gmail.com", "fhrs:id": "365094", "food": "yes", "name": "Albert Arms", "opening_hours": "Mo-Tu 16:00-22:00; We-Th 12:00-22:00; Fr-Sa 12:00-24:00; Su 12:00-20:30", "phone": "+44 20 3337 0313", "source:addr": "FHRS Open Data", "website": "https://www.thealbertarms.co.uk/"}}, {"type": "node", "id": 13055089159, "lat": 51.4957906, "lon": -0.1008687, "tags": {"addr:housenumber": "70", "addr:postcode": "SE1 6LW", "addr:street": "London Road", "amenity": "cafe", "check_date": "2026-06-06", "cuisine": "coffee_shop;sandwich;curry;samosa", "indoor_seating": "no", "name": "G Cafe", "outdoor_seating": "no", "phone": "+44 20 7378 7174", "takeaway": "only", "wheelchair": "yes"}}, {"type": "node", "id": 13630306850, "lat": 51.4973004, "lon": -0.1033655, "tags": {"check_date": "2026-06-01", "female:signed": "no", "male:signed": "no", "name": "Short Cuts Salon", "shop": "hairdresser"}}, {"type": "node", "id": 13630306851, "lat": 51.497344, "lon": -0.103416, "tags": {"amenity": "fast_food", "check_date": "2026-06-01", "cuisine": "chicken", "name": "HFC Chicken"}}, {"type": "node", "id": 13630306852, "lat": 51.4973883, "lon": -0.1034728, "tags": {"amenity": "cafe", "brand": "Mooboo", "brand:wikidata": "Q130244003", "check_date": "2026-06-01", "cuisine": "bubble_tea", "name": "Mooboo", "takeaway": "yes"}}, {"type": "node", "id": 13634476522, "lat": 51.4963167, "lon": -0.101527, "tags": {"amenity": "bench", "backrest": "yes"}}, {"type": "node", "id": 13634476523, "lat": 51.4963723, "lon": -0.1015788, "tags": {"amenity": "bench", "backrest": "yes"}}, {"type": "node", "id": 13910213218, "lat": 51.497028, "lon": -0.1024995, "tags": {"amenity": "telephone", "man_made": "telephone_box"}}, {"type": "node", "id": 13910213224, "lat": 51.4965008, "lon": -0.1018248, "tags": {"access": "yes", "amenity": "bicycle_parking", "bicycle_parking": "stands", "capacity": "6", "covered": "no", "fee": "no"}}, {"type": "node", "id": 13922884389, "lat": 51.4957455, "lon": -0.1039586, "tags": {"addr:housenumber": "55", "addr:street": "St George's Road", "check_date": "2026-06-09", "name": "The Butterfly Salon", "shop": "beauty"}}, {"type": "way", "id": 8171114, "center": {"lat": 51.4969471, "lon": -0.1016517}, "nodes": [60909689, 60909684, 60909681, 60909676, 60909697, 60909689], "tags": {"amenity": "court_yard"}}, {"type": "way", "id": 24397610, "center": {"lat": 51.4959485, "lon": -0.1056407}, "nodes": [264790795, 264790796, 10556730619, 986832192, 986832047, 10556730618, 10556730617, 986832341, 10556730616, 10556730615, 13923052302, 13922918499, 264790797, 11397561404, 11397561403, 11397561405, 264790798, 264790795], "tags": {"addr:city": "London", "addr:postcode": "SE11 4SN", "addr:street": "West Square", "amenity": "school", "capacity": "236", "check_date": "2025-08-30", "isced:level": "0;1", "max_age": "11", "min_age": "3", "name": "Charlotte Sharman Primary School", "phone": "+44 20 77355598", "ref:GB:uprn": "200003496848", "ref:edubase": "100816", "religion": "none", "school": "primary", "school:boarding": "no", "school:gender": "mixed", "school:selective": "no", "school:type": "foundation", "source:addr:postcode": "get-information-schools.service.gov.uk", "website": "https://www.charlottesharman.co.uk/", "wikidata": "Q66220922"}}, {"type": "way", "id": 71921020, "center": {"lat": 51.4945165, "lon": -0.1018219}, "nodes": [854857868, 854855133, 297700277, 6896299620, 6896299611, 6896299612, 6896299638, 8942303238, 6896299639, 6896299637, 8942303245, 6896299643, 6896299614, 10181001672, 13923781500, 6896299613, 3390681153, 10181001668, 3390681159, 3390681158, 12718323472, 12718323471, 10181001669, 3390681157, 854855172, 12718323454, 6896293454, 3071561925, 6896299607, 6896299608, 6896299609, 6896299610, 2507719575, 3071561926, 8942303257, 854857868], "tags": {"addr:city": "London", "addr:postcode": "SE1 6SB", "amenity": "university", "check_date": "2024-08-07", "name": "London College of Communication", "operator": "University of the Arts London", "phone": "+44 20 7514 6500", "website": "https://www.arts.ac.uk/lcc", "wikidata": "Q3258944", "wikipedia": "en:London College of Communication"}}, {"type": "way", "id": 89833590, "center": {"lat": 51.4957428, "lon": -0.1025906}, "nodes": [1041308343, 1041308325, 4501156972, 1041308134, 1041308225, 1041308343], "tags": {"addr:city": "London", "addr:country": "GB", "addr:housenumber": "1", "addr:postcode": "SE1 6HH", "addr:street": "Princess Street", "addr:suburb": "Southwark", "amenity": "place_of_worship", "building": "yes", "denomination": "salvation_army", "email": "southwark@salvationarmy.org.uk", "name": "The Salvation Army Community Church", "phone": "+44 20 7928 7136", "religion": "christian", "website": "https://www.salvationarmy.org.uk/southwark"}}, {"type": "way", "id": 102702457, "center": {"lat": 51.4942231, "lon": -0.1031703}, "nodes": [1186174648, 11397594096, 13316484274, 13316484275, 11397594097, 11397594098, 13316484276, 13316484273, 1186174648], "tags": {"amenity": "parking"}}, {"type": "way", "id": 331964837, "center": {"lat": 51.495163, "lon": -0.1020768}, "nodes": [3390681153, 3390681154, 3390681155, 8942303253, 6896293474, 8942303254, 6896299605, 6896299606, 3390681157, 10181001669, 12718323471, 12718323472, 3390681158, 3390681159, 10181001668, 3390681153], "tags": {"amenity": "parking", "parking": "surface"}}, {"type": "way", "id": 966551641, "center": {"lat": 51.4940688, "lon": -0.1015165}, "nodes": [8942303864, 8942303863, 297700280, 296154281, 296154282, 296154283, 8942303855, 8942303854, 296154286, 296154276, 8942303852, 8942303853, 296154278, 296154279, 296154280, 297700277, 6896299620, 6896299611, 8942303870, 8942303865, 8942303864], "tags": {"amenity": "parking"}}, {"type": "way", "id": 988447902, "center": {"lat": 51.4967136, "lon": -0.1033549}, "nodes": [9136430529, 9136430530, 9136430531, 9136430532, 9136430529], "tags": {"amenity": "parking"}}, {"type": "way", "id": 988447903, "center": {"lat": 51.4964966, "lon": -0.1032412}, "nodes": [9136430533, 9136430534, 9136430535, 9136430536, 9136430533], "tags": {"amenity": "parking"}}]}